{
  "name": "Master of Business Information Systems",
  "code": "7417XMBIS",
  "year": 2015,
  "units": 96,
  "required": {
    "compulsory_courses": [
      "BUSN7024",
      "BUSN8062",
      "COMP6240",
      "COMP6340",
      "INFS7004",
      "INFS7007",
      "INFS7040",
      "INFS8004",
      "INFS8205"
    ],
    "x_from_here": [
      {
        "type": "minimum",
        "units": 24,
        "courses": [
          "BUSN7008",
          "BUSI7019",
          "COMP6390",
          "COMP6470",
          "COMP6700",
          "MGMT7030",
          "MKTG7001"
        ]
      },
      {
        "type": "minimum",
        "units": 18,
        "courses": [
          "BUSN7017",
          "BUSN7045",
          "BUSN8102",
          "BUSN8802",
          "INFS8201",
          "MKTG7035"
        ]
      }
    ],
    "one_from_m/m/s": [],
    "required_m/m/s": []
  }
}