{
  "code": "BACTS-AACRD",
  "2014": [
    [
      {
        "code": "COMP1130",
        "level": "Introduction to Advanced Computing I",
        "units": "6 units"
      },
      {
        "code": "COMP2300",
        "level": "Introduction to Computer Systems",
        "units": "6 units"
      },
      {
        "code": "MATH1115",
        "level": "Mathematics and Applications 1 Honours",
        "units": "6 units"
      },
      {
        "code": "STAT1008",
        "level": "Quantitative Research Methods",
        "units": "6 units"
      }
    ],
    [
      {
        "code": "COMP1140",
        "level": "Introduction to Advanced Computing II",
        "units": "6 units"
      },
      {
        "code": "COMP2600",
        "level": "Formal Methods in Software Engineering",
        "units": "6 units"
      },
      {
        "code": "MATH1116",
        "level": "Mathematics and Applications 2 Honours",
        "units": "6 units"
      },
      {
        "code": "ECON1101",
        "level": "Microeconomics 1",
        "units": "6 units"
      }
    ],
    [
      {
        "code": "COMP2100",
        "level": "Software Construction",
        "units": "6 units"
      },
      {
        "code": "COMP2550",
        "level": "Advanced Computing R&D Methods",
        "units": "6 units"
      },
      {
        "code": "STAT1003",
        "level": "Statistical Techniques",
        "units": "6 units"
      },
      {
        "code": "STAT2001",
        "level": "Introductory Mathematical Statistics",
        "units": "6 units"
      }
    ],
    [
      {
        "code": "COMP2130",
        "level": "Software Analysis and Design",
        "units": "6 units"
      },
      {
        "code": "COMP2310",
        "level": "Concurrent and Distributed Systems",
        "units": "6 units"
      },
      {
        "code": "COMP2560",
        "level": "Studies in Advanced Computing R&D",
        "units": "6 units"
      },
      {
        "code": "ECON1102",
        "level": "Macroeconomics 1",
        "units": "6 units"
      }
    ],
    [
      {
        "code": "COMP3120",
        "level": "Managing Software Development",
        "units": "6 units"
      },
      {
        "code": "COMP3530",
        "level": "Systems Engineering for Software Engineers",
        "units": "6 units"
      },
      {
        "code": "STAT2008",
        "level": "Regression Modelling",
        "units": "6 units"
      },
      {
        "code": "STAT2032",
        "level": "Financial Mathematics",
        "units": "6 units"
      }
    ],
    [
      {
        "code": "COMP3600",
        "level": "Algorithms",
        "units": "6 units"
      },
      {
        "code": "MGMT3027",
        "level": "Entrepreneurship and Innovation",
        "units": "6 units"
      },
      {
        "code": "STAT3004",
        "level": "Stochastic Modelling",
        "units": "6 units"
      },
      {
        "code": "ECON2102",
        "level": "Macroeconomics 2(P)",
        "units": "6 units"
      }
    ],
    [
      {
        "code": "COMP3550",
        "level": "Advanced Computing R&D Project",
        "units": "12 units"
      },
      {
        "code": "COMP3630",
        "level": "Theory of Computation",
        "units": "6 units"
      },
      {
        "code": "BUSN1001",
        "level": "Business Reporting and Analysis",
        "units": "6 units"
      },
      {
        "code": "STAT3035",
        "level": "Risk Theory",
        "units": "6 units"
      }
    ],
    [
      {
        "code": "COMP3550",
        "level": "Advanced Computing R&D Project",
        "units": "12 units"
      },
      {
        "code": "COMP 3000/4000 elective",
        "units": "6 units\r"
      },
      {
        "code": "STAT3032",
        "level": "Survival Models",
        "units": "6 units"
      },
      {
        "code": "STAT3036",
        "level": "Credibility Theory",
        "units": "6 units"
      }
    ],
    [
      {
        "code": "COMP4550",
        "level": "Advanced Computing Research Project",
        "units": "24 units"
      },
      {
        "code": "COMP4550"
      },
      {
        "code": "COMP 3000/4000 elective",
        "units": "6 units\r"
      },
      {
        "code": "STAT3037",
        "level": "Life Contingencies",
        "units": "6 units"
      }
    ],
    [
      {
        "code": "COMP4550",
        "level": "Advanced Computing Research Project",
        "units": "24 units"
      },
      {
        "code": "COMP4550"
      },
      {
        "code": "COMP 3000/4000 elective",
        "units": "6 units"
      },
      {
        "code": "STAT3038",
        "level": "Actuarial Techniques",
        "units": "6 units"
      }
    ]
  ],
  "2015": [
    [
      {
        "code": "COMP1130",
        "level": "Introduction to Programming and Algorithms (Advanced)",
        "units": "6 units"
      },
      {
        "code": "COMP2300",
        "level": "Introduction to Computer Systems",
        "units": "6 units"
      },
      {
        "code": "MATH1115",
        "level": "Advanced Mathematics and Applications 1",
        "units": "6 units"
      },
      {
        "code": "STAT1008",
        "level": "Quantitative Research Methods",
        "units": "6 units"
      }
    ],
    [
      {
        "code": "COMP1140",
        "level": "Introduction to Software Systems (Advanced)",
        "units": "6 units"
      },
      {
        "code": "COMP2600",
        "level": "Formal Methods in Software Engineering",
        "units": "6 units"
      },
      {
        "code": "MATH1116",
        "level": "Advanced Mathematics and Applications  2",
        "units": "6 units"
      },
      {
        "code": "ECON1101",
        "level": "Microeconomics 1",
        "units": "6 units"
      }
    ],
    [
      {
        "code": "COMP2100",
        "level": "Software Construction",
        "units": "6 units"
      },
      {
        "code": "COMP2550",
        "level": "Advanced Computing R&D Methods",
        "units": "6 units"
      },
      {
        "code": "STAT1003",
        "level": "Statistical Techniques",
        "units": "6 units"
      },
      {
        "code": "STAT2001",
        "level": "Introductory Mathematical Statistics",
        "units": "6 units"
      }
    ],
    [
      {
        "code": "COMP2130",
        "level": "Software Analysis and Design",
        "units": "6 units"
      },
      {
        "code": "COMP2310",
        "level": "Concurrent and Distributed Systems",
        "units": "6 units"
      },
      {
        "code": "COMP2560",
        "level": "Studies in Advanced Computing R&D",
        "units": "6 units"
      },
      {
        "code": "ECON1102",
        "level": "Macroeconomics 1",
        "units": "6 units"
      }
    ],
    [
      {
        "code": "COMP3120",
        "level": "Managing Software Development",
        "units": "6 units"
      },
      {
        "code": "COMP3530",
        "level": "Systems Engineering for Software Engineers",
        "units": "6 units"
      },
      {
        "code": "STAT2008",
        "level": "Regression Modelling",
        "units": "6 units"
      },
      {
        "code": "STAT2032",
        "level": "Financial Mathematics",
        "units": "6 units"
      }
    ],
    [
      {
        "code": "COMP3600",
        "level": "Algorithms",
        "units": "6 units"
      },
      {
        "code": "MGMT3027",
        "level": "Entrepreneurship and Innovation",
        "units": "6 units"
      },
      {
        "code": "STAT3004",
        "level": "Stochastic Modelling",
        "units": "6 units"
      },
      {
        "code": "ECON2102",
        "level": "Macroeconomics 2(P)",
        "units": "6 units"
      }
    ],
    [
      {
        "code": "COMP3550",
        "level": "Advanced Computing R&D Project",
        "units": "6 units"
      },
      {
        "code": "COMP3630",
        "level": "Theory of Computation",
        "units": "6 units"
      },
      {
        "code": "BUSN1001",
        "level": "Business Reporting and Analysis",
        "units": "6 units"
      },
      {
        "code": "STAT3035",
        "level": "Risk Theory",
        "units": "6 units"
      }
    ],
    [
      {
        "code": "COMP3550",
        "level": "Advanced Computing R&D Project",
        "units": "6 units"
      },
      {
        "code": "COMP 3000/4000 elective",
        "units": "6 units\r"
      },
      {
        "code": "STAT3032",
        "level": "Survival Models",
        "units": "6 units"
      },
      {
        "code": "STAT3036",
        "level": "Credibility Theory",
        "units": "6 units"
      }
    ],
    [
      {
        "code": "COMP4550",
        "level": "Advanced Computing Research Project",
        "units": "12 units"
      },
      {
        "code": "COMP4550"
      },
      {
        "code": "COMP 3000/4000 elective",
        "units": "6 units\r"
      },
      {
        "code": "STAT3037",
        "level": "Life Contingencies",
        "units": "6 units"
      }
    ],
    [
      {
        "code": "COMP4550",
        "level": "Advanced Computing Research Project",
        "units": "12 units"
      },
      {
        "code": "COMP4550"
      },
      {
        "code": "COMP 3000/4000 elective",
        "units": "6 units"
      },
      {
        "code": "STAT3038",
        "level": "Actuarial Techniques",
        "units": "6 units"
      }
    ]
  ],
  "2016": [
    [
      {
        "code": "COMP1130",
        "level": "Introduction to Programming and Algorithms (Advanced)",
        "units": "6 units"
      },
      {
        "code": "STAT1003",
        "level": "Statistical Techniques",
        "units": "6 units"
      },
      {
        "code": "MATH1115",
        "level": "Advanced Mathematics and Applications 1",
        "units": "6 units"
      },
      {
        "code": "STAT1008",
        "level": "Quantitative Research Methods",
        "units": "6 units"
      }
    ],
    [
      {
        "code": "COMP1140",
        "level": "Introduction to Software Systems (Advanced)",
        "units": "6 units"
      },
      {
        "code": "COMP2600",
        "level": "Formal Methods in Software Engineering",
        "units": "6 units"
      },
      {
        "code": "MATH1116",
        "level": "Advanced Mathematics and Applications  2",
        "units": "6 units"
      },
      {
        "code": "ECON1101",
        "level": "Microeconomics 1",
        "units": "6 units"
      }
    ],
    [
      {
        "code": "COMP2100",
        "level": "Software Construction",
        "units": "6 units"
      },
      {
        "code": "COMP2550",
        "level": "Advanced Computing R&D Methods",
        "units": "6 units"
      },
      {
        "code": "COMP2300",
        "level": "Introduction to Computer Systems",
        "units": "6 units"
      },
      {
        "code": "STAT2001",
        "level": "Introductory Mathematical Statistics",
        "units": "6 units"
      }
    ],
    [
      {
        "code": "COMP2130",
        "level": "Software Analysis and Design",
        "units": "6 units"
      },
      {
        "code": "COMP2310",
        "level": "Concurrent and Distributed Systems",
        "units": "6 units"
      },
      {
        "code": "COMP2560",
        "level": "Studies in Advanced Computing R&D",
        "units": "6 units"
      },
      {
        "code": "ECON1102",
        "level": "Macroeconomics 1",
        "units": "6 units"
      }
    ],
    [
      {
        "code": "COMP3120",
        "level": "Managing Software Development",
        "units": "6 units"
      },
      {
        "code": "COMP3530",
        "level": "Systems Engineering for Software Engineers",
        "units": "6 units"
      },
      {
        "code": "STAT2008",
        "level": "Regression Modelling",
        "units": "6 units"
      },
      {
        "code": "STAT2032",
        "level": "Financial Mathematics",
        "units": "6 units"
      }
    ],
    [
      {
        "code": "COMP3600",
        "level": "Algorithms",
        "units": "6 units"
      },
      {
        "code": "MGMT3027",
        "level": "Entrepreneurship and Innovation",
        "units": "6 units"
      },
      {
        "code": "STAT3004",
        "level": "Stochastic Modelling",
        "units": "6 units"
      },
      {
        "code": "ECON2102",
        "level": "Macroeconomics 2(P)",
        "units": "6 units"
      }
    ],
    [
      {
        "code": "COMP3550",
        "level": "Advanced Computing R&D Project",
        "units": "6 units"
      },
      {
        "code": "COMP3630",
        "level": "Theory of Computation",
        "units": "6 units"
      },
      {
        "code": "BUSN1001",
        "level": "Business Reporting and Analysis",
        "units": "6 units"
      },
      {
        "code": "STAT3035",
        "level": "Risk Theory",
        "units": "6 units"
      }
    ],
    [
      {
        "code": "COMP3550",
        "level": "Advanced Computing R&D Project",
        "units": "6 units"
      },
      {
        "code": "COMP 3000/4000 elective",
        "units": "6 units\r"
      },
      {
        "code": "STAT3032",
        "level": "Survival Models",
        "units": "6 units"
      },
      {
        "code": "STAT3036",
        "level": "Credibility Theory",
        "units": "6 units"
      }
    ],
    [
      {
        "code": "COMP4550",
        "level": "Advanced Computing Research Project",
        "units": "12 units"
      },
      {
        "code": "COMP4550"
      },
      {
        "code": "COMP 3000/4000 elective",
        "units": "6 units\r"
      },
      {
        "code": "STAT3037",
        "level": "Life Contingencies",
        "units": "6 units"
      }
    ],
    [
      {
        "code": "COMP4550",
        "level": "Advanced Computing Research Project",
        "units": "12 units"
      },
      {
        "code": "COMP4550"
      },
      {
        "code": "COMP 3000/4000 elective",
        "units": "6 units"
      },
      {
        "code": "STAT3038",
        "level": "Actuarial Techniques",
        "units": "6 units"
      }
    ]
  ],
  "2017": [
    [
      {
        "code": "COMP1130",
        "level": "Programming as Problem Solving (Advanced)",
        "units": "6 units"
      },
      {
        "code": "STAT1003",
        "level": "Statistical Techniques",
        "units": "6 units"
      },
      {
        "code": "MATH1115",
        "level": "Advanced Mathematics and Applications 1",
        "units": "6 units"
      },
      {
        "code": "STAT1008",
        "level": "Quantitative Research Methods",
        "units": "6 units"
      }
    ],
    [
      {
        "code": "COMP1140",
        "level": "Structured Programming (Advanced)",
        "units": "6 units"
      },
      {
        "code": "COMP2600"
      },
      {
        "code": "MATH1116",
        "level": "Advanced Mathematics and Applications  2",
        "units": "6 units"
      },
      {
        "code": "ECON1101",
        "level": "Microeconomics 1",
        "units": "6 units"
      }
    ],
    [
      {
        "code": "COMP2100",
        "level": "Software Design Methodologies",
        "units": "6 units"
      },
      {
        "code": "COMP2550",
        "level": "Advanced Computing R&D Methods",
        "units": "6 units"
      },
      {
        "code": "COMP2300",
        "level": "Computer Organisation and Program Execution",
        "units": "6 units"
      },
      {
        "code": "STAT2001",
        "level": "Introductory Mathematical Statistics",
        "units": "6 units"
      }
    ],
    [
      {
        "code": "COMP2130",
        "level": "Software Analysis and Design",
        "units": "6 units"
      },
      {
        "code": "COMP2310",
        "level": "Systems, Networks and Concurrency",
        "units": "6 units"
      },
      {
        "code": "COMP2560",
        "level": "Studies in Advanced Computing R&D",
        "units": "6 units"
      },
      {
        "code": "ECON1102",
        "level": "Macroeconomics 1",
        "units": "6 units"
      }
    ],
    [
      {
        "code": "COMP3120",
        "level": "Managing Software Development",
        "units": "6 units"
      },
      {
        "code": "COMP3530",
        "level": "Systems Engineering for Software Engineers",
        "units": "6 units"
      },
      {
        "code": "STAT2008",
        "level": "Regression Modelling",
        "units": "6 units"
      },
      {
        "code": "STAT2032",
        "level": "Financial Mathematics",
        "units": "6 units"
      }
    ],
    [
      {
        "code": "COMP3600",
        "level": "Algorithms",
        "units": "6 units"
      },
      {
        "code": "MGMT3027",
        "level": "Entrepreneurship and Innovation",
        "units": "6 units"
      },
      {
        "code": "STAT2005",
        "level": "Introduction to Stochastic Processes",
        "units": "6 units"
      },
      {
        "code": "ECON2102",
        "level": "Macroeconomics 2(P)",
        "units": "6 units"
      }
    ],
    [
      {
        "code": "COMP3550",
        "level": "Advanced Computing R&D Project",
        "units": "6 units"
      },
      {
        "code": "COMP3630",
        "level": "Theory of Computation",
        "units": "6 units"
      },
      {
        "code": "BUSN1001",
        "level": "Business Reporting and Analysis",
        "units": "6 units"
      },
      {
        "code": "STAT3035",
        "level": "Risk Theory",
        "units": "6 units"
      }
    ],
    [
      {
        "code": "COMP3550",
        "level": "Advanced Computing R&D Project",
        "units": "6 units"
      },
      {
        "code": "COMP 3000/4000 elective",
        "units": "6 units\r"
      },
      {
        "code": "STAT3032",
        "level": "Survival Models",
        "units": "6 units"
      },
      {
        "code": "STAT3036",
        "level": "Credibility Theory",
        "units": "6 units"
      }
    ],
    [
      {
        "code": "COMP4550",
        "level": "Advanced Computing Research Project",
        "units": "12 units"
      },
      {
        "code": "COMP4550"
      },
      {
        "code": "COMP 3000/4000 elective",
        "units": "6 units\r"
      },
      {
        "code": "STAT3037",
        "level": "Life Contingencies",
        "units": "6 units"
      }
    ],
    [
      {
        "code": "COMP4550",
        "level": "Advanced Computing Research Project",
        "units": "12 units"
      },
      {
        "code": "COMP4550"
      },
      {
        "code": "COMP 3000/4000 elective",
        "units": "6 units"
      },
      {
        "code": "STAT3038",
        "level": "Actuarial Techniques",
        "units": "6 units"
      }
    ]
  ],
  "2018": [
    [
      {
        "code": "COMP1130",
        "level": "Programming as Problem Solving (Advanced)",
        "units": "6 units"
      },
      {
        "code": "MATH1005",
        "level": "Discrete Mathematical Models",
        "units": "6 units"
      },
      {
        "code": "MATH1115",
        "level": "Advanced Mathematics and Applications 1",
        "units": "6 units"
      },
      {}
    ],
    [
      {
        "code": "COMP1140",
        "level": "Structured Programming (Advanced)",
        "units": "6 units"
      },
      {
        "code": "COMP1600",
        "level": "Foundations of Computing",
        "units": "6 units"
      },
      {
        "code": "MATH1116",
        "level": "Advanced Mathematics and Applications  2",
        "units": "6 units"
      },
      {}
    ],
    [
      {
        "code": "COMP2100",
        "level": "Software Design Methodologies",
        "units": "6 units"
      },
      {
        "code": "COMP2550",
        "level": "Advanced Computing R&D Methods",
        "units": "6 units"
      },
      {
        "code": "COMP2300",
        "level": "Computer Organisation and Program Execution",
        "units": "6 units"
      },
      {}
    ],
    [
      {
        "code": "COMP2120",
        "level": "Software Engineering",
        "units": "6 units"
      },
      {
        "code": "COMP2310",
        "level": "Systems, Networks and Concurrency",
        "units": "6 units"
      },
      {
        "code": "COMP2560",
        "level": "Studies in Advanced Computing R&D",
        "units": "6 units"
      },
      {}
    ],
    [
      {
        "code": "COMP2420",
        "level": "Introduction to Data Management, Analysis and Security",
        "units": "6 units"
      },
      {
        "code": "Computing Research Specialisation",
        "units": "6 units"
      },
      {},
      {}
    ],
    [
      {
        "code": "COMP3600",
        "level": "Algorithms",
        "units": "6 units"
      },
      {
        "code": "Computing Research Specialisation",
        "units": "6 units"
      },
      {},
      {}
    ],
    [
      {
        "code": "COMP3770",
        "level": "Individual Research Project",
        "units": "6 units"
      },
      {
        "code": "Computing Research Specialisation",
        "units": "6 units"
      },
      {},
      {}
    ],
    [
      {
        "code": "COMP3770",
        "level": "Individual Research Project",
        "units": "6 units"
      },
      {
        "code": "Computing Research Specialisation",
        "units": "6 units\r"
      },
      {},
      {}
    ],
    [
      {
        "code": "COMP4550",
        "level": "Advanced Computing Research Project",
        "units": "12 units"
      },
      {
        "code": "COMP4550"
      },
      {},
      {}
    ],
    [
      {
        "code": "COMP4550",
        "level": "Advanced Computing Research Project",
        "units": "12 units"
      },
      {
        "code": "COMP4550"
      },
      {},
      {}
    ]
  ],
  "2019": [
    [
      {
        "code": "COMP1130",
        "level": "Programming as Problem Solving (Advanced)",
        "units": "6 units"
      },
      {
        "code": "MATH1005",
        "level": "Discrete Mathematical Models",
        "units": "6 units"
      },
      {
        "code": "MATH1115",
        "level": "Advanced Mathematics and Applications 1",
        "units": "6 units"
      },
      {}
    ],
    [
      {
        "code": "COMP1140",
        "level": "Structured Programming (Advanced)",
        "units": "6 units"
      },
      {
        "code": "COMP1600",
        "level": "Foundations of Computing",
        "units": "6 units"
      },
      {
        "code": "MATH1116",
        "level": "Advanced Mathematics and Applications  2",
        "units": "6 units"
      },
      {}
    ],
    [
      {
        "code": "COMP2100",
        "level": "Software Design Methodologies",
        "units": "6 units"
      },
      {
        "code": "COMP2550",
        "level": "Advanced Computing R&D Methods",
        "units": "6 units"
      },
      {
        "code": "COMP2300",
        "level": "Computer Organisation and Program Execution",
        "units": "6 units"
      },
      {}
    ],
    [
      {
        "code": "COMP2120",
        "level": "Software Engineering",
        "units": "6 units"
      },
      {
        "code": "COMP2310",
        "level": "Systems, Networks and Concurrency",
        "units": "6 units"
      },
      {
        "code": "COMP2560",
        "level": "Studies in Advanced Computing R&D",
        "units": "6 units"
      },
      {}
    ],
    [
      {
        "code": "COMP2420",
        "level": "Introduction to Data Management, Analysis and Security",
        "units": "6 units"
      },
      {
        "code": "Computing Research Specialisation",
        "units": "6 units"
      },
      {},
      {}
    ],
    [
      {
        "code": "COMP3600",
        "level": "Algorithms",
        "units": "6 units"
      },
      {
        "code": "Computing Research Specialisation",
        "units": "6 units"
      },
      {},
      {}
    ],
    [
      {
        "code": "COMP3770",
        "level": "Individual Research Project",
        "units": "6 units"
      },
      {
        "code": "Computing Research Specialisation",
        "units": "6 units"
      },
      {},
      {}
    ],
    [
      {
        "code": "COMP3770",
        "level": "Individual Research Project",
        "units": "6 units"
      },
      {
        "code": "Computing Research Specialisation",
        "units": "6 units\r"
      },
      {},
      {}
    ],
    [
      {
        "code": "COMP4550",
        "level": "Advanced Computing Research Project",
        "units": "12 units"
      },
      {
        "code": "COMP4550"
      },
      {},
      {}
    ],
    [
      {
        "code": "COMP4550",
        "level": "Advanced Computing Research Project",
        "units": "12 units"
      },
      {
        "code": "COMP4550"
      },
      {},
      {}
    ]
  ]
}